connectopy/__init__.py
connectopy/cli.py
connectopy/analysis/__init__.py
connectopy/analysis/dimorphism.py
connectopy/analysis/mediation.py
connectopy/analysis/pca.py
connectopy/analysis/vae.py
connectopy/data/__init__.py
connectopy/data/hcp_loader.py
connectopy/data/loader.py
connectopy/data/preprocessing.py
connectopy/models/__init__.py
connectopy/models/classifiers.py
connectopy/visualization/__init__.py
connectopy/visualization/plots.py
connectopy-0.1.0.dist-info/METADATA
connectopy-0.1.0.dist-info/WHEEL
connectopy-0.1.0.dist-info/entry_points.txt
connectopy-0.1.0.dist-info/top_level.txt
connectopy-0.1.0.dist-info/RECORD
