Metadata-Version: 2.4
Name: connectopy
Version: 0.1.0
Summary: Analysis of brain structural and functional connectomes from the Human Connectome Project
Author: Riley Harper, Sean Shen, Yinyu Yao
License: MIT
Project-URL: Homepage, https://github.com/Sean0418/connectopy
Project-URL: Documentation, https://connectopy.readthedocs.io
Project-URL: Repository, https://github.com/Sean0418/connectopy
Keywords: brain,connectome,neuroscience,HCP,fMRI,DTI
Classifier: Development Status :: 3 - Alpha
Classifier: Intended Audience :: Science/Research
Classifier: License :: OSI Approved :: MIT License
Classifier: Programming Language :: Python :: 3
Classifier: Programming Language :: Python :: 3.9
Classifier: Programming Language :: Python :: 3.10
Classifier: Programming Language :: Python :: 3.11
Classifier: Programming Language :: Python :: 3.12
Classifier: Topic :: Scientific/Engineering :: Bio-Informatics
Classifier: Topic :: Scientific/Engineering :: Medical Science Apps.
Requires-Python: >=3.9
Requires-Dist: numpy>=1.21.0
Requires-Dist: pandas>=1.3.0
Requires-Dist: scipy>=1.7.0
Requires-Dist: scikit-learn>=1.0.0
Requires-Dist: matplotlib>=3.4.0
Requires-Dist: seaborn>=0.11.0
Requires-Dist: h5py>=3.0.0
Requires-Dist: torch>=1.9.0
Requires-Dist: xgboost>=1.5.0
Requires-Dist: interpret>=0.5.0
Requires-Dist: tqdm>=4.60.0
Provides-Extra: dev
Requires-Dist: pytest>=7.0.0; extra == "dev"
Requires-Dist: pytest-cov>=4.0.0; extra == "dev"
Requires-Dist: ruff>=0.1.0; extra == "dev"
Requires-Dist: mypy>=1.0.0; extra == "dev"
Requires-Dist: pre-commit>=3.0.0; extra == "dev"
Requires-Dist: pandas-stubs>=2.0.0; extra == "dev"
Requires-Dist: types-tqdm>=4.60.0; extra == "dev"
Provides-Extra: resampling
Requires-Dist: imbalanced-learn>=0.10.0; extra == "resampling"
Provides-Extra: docs
Requires-Dist: sphinx>=6.0.0; extra == "docs"
Requires-Dist: sphinx-rtd-theme>=1.0.0; extra == "docs"
Requires-Dist: sphinx-autodoc-typehints>=1.20.0; extra == "docs"
Requires-Dist: myst-parser>=1.0.0; extra == "docs"
